napari_pitcount_cfim/__init__.py
napari_pitcount_cfim/_dock_widget.py
napari_pitcount_cfim/loggers.py
napari_pitcount_cfim/napari.yaml
napari_pitcount_cfim/segmentation_worker.py
napari_pitcount_cfim/start_plugin.py
napari_pitcount_cfim/cellpose_analysis/__init__.py
napari_pitcount_cfim/cellpose_analysis/cellpose_user.py
napari_pitcount_cfim/config/__init__.py
napari_pitcount_cfim/config/settings_handler.py
napari_pitcount_cfim/config/settings_structure.py
napari_pitcount_cfim/image_handling/__init__.py
napari_pitcount_cfim/image_handling/image_handler.py
napari_pitcount_cfim/library_workarounds/RangeDict.py
napari_pitcount_cfim/library_workarounds/__init__.py
napari_pitcount_cfim/pitcounter/__init__.py
napari_pitcount_cfim/pitcounter/predict_user.py
napari_pitcount_cfim/pitcounter/transformers.py
napari_pitcount_cfim/result_handling/__init__.py
napari_pitcount_cfim/result_handling/graphs.py
napari_pitcount_cfim/result_handling/result_handler.py
napari_pitcount_cfim-1.0.0.dist-info/licenses/LICENSE
napari_pitcount_cfim-1.0.0.dist-info/METADATA
napari_pitcount_cfim-1.0.0.dist-info/WHEEL
napari_pitcount_cfim-1.0.0.dist-info/entry_points.txt
napari_pitcount_cfim-1.0.0.dist-info/top_level.txt
napari_pitcount_cfim-1.0.0.dist-info/RECORD
