Metadata-Version: 2.4
Name: napari-pitcount-cfim
Version: 1.0.0
Summary: A pipeline for stuff #TODO: Get knowledge to write a proper description Pitcount
Home-page: https://github.com/MaxusTheOne/napari-pitcount-cfim
Author: Markus L. Bille
Author-email: github+markus@bille.dk
License: BSD-3-Clause
Classifier: Development Status :: 4 - Beta
Classifier: Framework :: napari
Classifier: Intended Audience :: Science/Research
Classifier: License :: OSI Approved :: BSD License
Classifier: Operating System :: OS Independent
Classifier: Programming Language :: Python
Classifier: Topic :: Scientific/Engineering :: Image Processing
Requires-Python: >=3.9
License-File: LICENSE
Requires-Dist: QtPy
Requires-Dist: pydantic
Requires-Dist: xmltodict
Requires-Dist: napari-czi-reader
Requires-Dist: aicsimageio
Requires-Dist: aicspylibczi
Requires-Dist: czifile
Requires-Dist: matplotlib
Requires-Dist: adjustText
Requires-Dist: cellpose<4.0.0
Requires-Dist: tensorflow
Requires-Dist: joblib
Requires-Dist: torch
Requires-Dist: torchvision
Provides-Extra: napari
Requires-Dist: napari[all]; extra == "napari"
Provides-Extra: test
Requires-Dist: pytest; extra == "test"
Requires-Dist: pytest-cov; extra == "test"
Requires-Dist: pytest-qt; extra == "test"
Requires-Dist: codecov; extra == "test"
Provides-Extra: dev
Requires-Dist: napari[all]; extra == "dev"
Requires-Dist: pytest; extra == "dev"
Requires-Dist: pytest-cov; extra == "dev"
Requires-Dist: pytest-qt; extra == "dev"
Requires-Dist: codecov; extra == "dev"
Dynamic: license-file
